setup.py
axat/Binomialdistribution.py
axat/Gaussiandistribution.py
axat/Generaldistribution.py
axat/__init__.py
axat.egg-info/PKG-INFO
axat.egg-info/SOURCES.txt
axat.egg-info/dependency_links.txt
axat.egg-info/not-zip-safe
axat.egg-info/top_level.txt