Metadata-Version: 1.0
Name: axat
Version: 1.0
Summary: Gaussian distributions
Home-page: UNKNOWN
Author: Akshat Anand
Author-email: UNKNOWN
License: UNKNOWN
Platform: UNKNOWN
